mssql_to_python3_orm/__init__.py
mssql_to_python3_orm/base_db_info.py
mssql_to_python3_orm/main.py
mssql_to_python3_orm/py2sql.py
mssql_to_python3_orm-1.2.0.dist-info/METADATA
mssql_to_python3_orm-1.2.0.dist-info/WHEEL
mssql_to_python3_orm-1.2.0.dist-info/entry_points.txt
mssql_to_python3_orm-1.2.0.dist-info/top_level.txt
mssql_to_python3_orm-1.2.0.dist-info/RECORD
