Metadata-Version: 2.1
Name: mssql-to-python3-orm
Version: 1.2.0
Summary: MS SQL Server to Python 3 ORM
Home-page: https://github.com/MaiiaChudinova/univ_metaprogramming
Author: Maiia Chudinova, Valeriia Yaroshenko, Dmitry Shvab
License: UNKNOWN
Platform: UNKNOWN
Requires-Dist: pyodbc
